get_data/__init__.py
get_data/get_data.py
get_data_example-0.0.4.dist-info/LICENCE
get_data_example-0.0.4.dist-info/METADATA
get_data_example-0.0.4.dist-info/WHEEL
get_data_example-0.0.4.dist-info/top_level.txt
get_data_example-0.0.4.dist-info/RECORD
